pydiscovergy/__init__.py
pydiscovergy/authentication/__init__.py
pydiscovergy/authentication/base.py
pydiscovergy/authentication/basicauth.py
pydiscovergy/authentication/token.py
pydiscovergy/const.py
pydiscovergy/discovergy.py
pydiscovergy/error.py
pydiscovergy/models.py
pydiscovergy/py.typed
pydiscovergy-3.0.1.dist-info/LICENSE
pydiscovergy-3.0.1.dist-info/METADATA
pydiscovergy-3.0.1.dist-info/WHEEL
pydiscovergy-3.0.1.dist-info/RECORD
