Metadata-Version: 2.1
Name: pydiscovergy
Version: 3.0.1
Summary: Async Python 3 library for interacting with Discovergy smart meters API
Home-page: https://github.com/jpbede/pydiscovergy
License: MIT
Keywords: discovergy,smart meter,smart home
Author: Jan-Philipp Benecke
Author-email: jan-philipp@bnck.me
Requires-Python: >=3.11,<4.0
Classifier: Development Status :: 5 - Production/Stable
Classifier: Framework :: AsyncIO
Classifier: Intended Audience :: Developers
Classifier: License :: OSI Approved :: MIT License
Classifier: Natural Language :: English
Classifier: Programming Language :: Python :: 3
Classifier: Programming Language :: Python :: 3.11
Classifier: Programming Language :: Python :: 3.12
Classifier: Topic :: Software Development :: Libraries :: Python Modules
Requires-Dist: authlib (>=0.15)
Requires-Dist: httpx (>=0.24)
Requires-Dist: mashumaro (>=3.11)
Requires-Dist: orjson (>=3.9.0)
Requires-Dist: pytz (>=2023.3)
Project-URL: Bug Tracker, https://github.com/jpbede/pydiscovergy/issues
Project-URL: Changelog, https://github.com/jpbede/pydiscovergy/releases
Project-URL: Repository, https://github.com/jpbede/pydiscovergy
